simpletokenizer/__init__.py
simpletokenizer/tokenization.py
simpletokenizer-0.1.2.dist-info/LICENSE
simpletokenizer-0.1.2.dist-info/METADATA
simpletokenizer-0.1.2.dist-info/WHEEL
simpletokenizer-0.1.2.dist-info/top_level.txt
simpletokenizer-0.1.2.dist-info/RECORD
