Metadata-Version: 2.1
Name: simpletokenizer
Version: 0.1.2
Summary: A small example package
Home-page: https://github.com/tdd-ai/simple-tokenizer/
Author: Ali Safaya
Author-email: alisafaya@gmail.com
License: UNKNOWN
Download-URL: https://github.com/tdd-ai/simple-tokenizer/archive/v0.1.2.tar.gz
Platform: UNKNOWN
Classifier: Topic :: Text Processing
Classifier: License :: OSI Approved :: MIT License
Classifier: Programming Language :: Python :: 3
Requires-Python: >=3.6
